briefcase_p4a_backend/__init__.py
briefcase_p4a_backend/p4a.py
briefcase_p4a_backend/platform.py
briefcase_p4a_backend/py.typed
briefcase_p4a_backend/recipes/pyjnius/__init__.py
briefcase_p4a_backend/recipes/pyjnius/python313_long_fix.patch
briefcase_p4a_backend-1.0.0.post1.dist-info/licenses/LICENSE
briefcase_p4a_backend-1.0.0.post1.dist-info/METADATA
briefcase_p4a_backend-1.0.0.post1.dist-info/WHEEL
briefcase_p4a_backend-1.0.0.post1.dist-info/entry_points.txt
briefcase_p4a_backend-1.0.0.post1.dist-info/top_level.txt
briefcase_p4a_backend-1.0.0.post1.dist-info/RECORD
