Metadata-Version: 2.4
Name: briefcase-p4a-backend
Version: 1.0.0.post1
Summary: Python-for-Android (P4A) backend for Briefcase
Author-email: Al pyCino <thealpycino@gmail.com>
Maintainer-email: Al pyCino <thealpycino@gmail.com>
License-Expression: MIT
Project-URL: Homepage, https://github.com/pyCino/briefcase-p4a-backend
Project-URL: Documentation, https://github.com/pyCino/briefcase-p4a-backend#readme
Project-URL: Repository, https://github.com/pyCino/briefcase-p4a-backend.git
Project-URL: Issues, https://github.com/pyCino/briefcase-p4a-backend/issues
Project-URL: Changelog, https://github.com/pyCino/briefcase-p4a-backend/blob/main/CHANGELOG.md
Keywords: briefcase,python-for-android,p4a,android,apk,mobile,packaging,build-tools,cross-platform
Classifier: Development Status :: 5 - Production/Stable
Classifier: Intended Audience :: Developers
Classifier: Operating System :: POSIX :: Linux
Classifier: Programming Language :: Python :: 3
Classifier: Programming Language :: Python :: 3.8
Classifier: Programming Language :: Python :: 3.9
Classifier: Programming Language :: Python :: 3.10
Classifier: Programming Language :: Python :: 3.11
Classifier: Programming Language :: Python :: 3.12
Classifier: Programming Language :: Python :: 3.13
Classifier: Topic :: Software Development :: Build Tools
Classifier: Topic :: Software Development :: Libraries :: Python Modules
Classifier: Topic :: System :: Software Distribution
Classifier: Topic :: System :: Archiving :: Packaging
Requires-Python: >=3.8
License-File: LICENSE
Requires-Dist: briefcase>=0.3.23
Requires-Dist: python-for-android>=2024.1.21
Requires-Dist: cookiecutter>=2.0.0
Requires-Dist: cython>=0.29.0
Provides-Extra: dev
Requires-Dist: pytest>=7.0.0; extra == "dev"
Requires-Dist: pytest-cov>=4.0.0; extra == "dev"
Requires-Dist: black>=23.0.0; extra == "dev"
Requires-Dist: flake8>=6.0.0; extra == "dev"
Requires-Dist: mypy>=1.0.0; extra == "dev"
Provides-Extra: docs
Requires-Dist: sphinx>=5.0.0; extra == "docs"
Requires-Dist: sphinx-rtd-theme>=1.0.0; extra == "docs"
Requires-Dist: myst-parser>=0.18.0; extra == "docs"
Dynamic: license-file
